[
  {
    "_id": "k30ckjtth",
    "title": "Nuevo producto inicial",
    "thumbnails": ["https://example.com/image.jpg"],
    "status": true,
    "brand": "Marca",
    "rating": "5",
    "color": "Rojo",
    "details": ["Detalle 1", "Detalle 2"],
    "description": ["Descripción 1", "Descripción 2"],
    "stock": 10,
    "freeshipping": true,
    "dues": [6, 12],
    "price": 99.99,
    "code": "ABC123"
  },
  {
    "_id": "256gvqvxo",
    "title": "Nuevo producto",
    "thumbnails": ["https://example.com/image.jpg"],
    "status": true,
    "brand": "Marca",
    "rating": "5",
    "color": "Rojo",
    "details": ["Detalle 1", "Detalle 2"],
    "description": ["Descripción 1", "Descripción 2"],
    "stock": 10,
    "freeshipping": true,
    "dues": [6, 12],
    "price": 99.99,
    "code": "ABC123"
  },
  {
    "_id": "im43xgebt",
    "title": "Nuevo producto",
    "thumbnails": ["https://example.com/image.jpg"],
    "status": true,
    "brand": "Marca",
    "rating": "5",
    "color": "Rojo",
    "details": ["Detalle 1", "Detalle 2"],
    "description": ["Descripción 1", "Descripción 2"],
    "stock": 10,
    "freeshipping": true,
    "dues": [6, 12],
    "price": 99.99,
    "code": "ABC123"
  },
  {
    "_id": "l1sm445bx",
    "title": "Nuevo producto",
    "thumbnails": ["https://example.com/image.jpg"],
    "status": true,
    "brand": "Marca",
    "rating": "5",
    "color": "Rojo",
    "details": ["Detalle 1", "Detalle 2"],
    "description": ["Descripción 1", "Descripción 2"],
    "stock": 10,
    "freeshipping": true,
    "dues": [6, 12],
    "price": 99.99,
    "code": "ABC123"
  },
  {
    "_id": "hq5eaevwi",
    "title": "Nuevo producto",
    "thumbnails": ["https://example.com/image.jpg"],
    "status": true,
    "brand": "Marca",
    "rating": "5",
    "color": "Rojo",
    "details": ["Detalle 1", "Detalle 2"],
    "description": ["Descripción 1", "Descripción 2"],
    "stock": 10,
    "freeshipping": true,
    "dues": [6, 12],
    "price": 99.99,
    "code": "ABC123"
  }
]
